COPYING
MANIFEST.in
Makefile
README.md
pyproject.toml
setup.cfg
setup.py
configs/Fedora/fedora.toml
configs/Fedora/licenses.toml
configs/Fedora/scoring.toml
configs/Fedora/users-groups.toml
configs/Fedora/warn-on-functions.toml
configs/openSUSE/dbus-services.toml
configs/openSUSE/licenses.toml
configs/openSUSE/opensuse.toml
configs/openSUSE/pam-modules.toml
configs/openSUSE/pie-executables.toml
configs/openSUSE/scoring.toml
configs/openSUSE/users-groups.toml
rpmlint/__init__.py
rpmlint/__isocodes__.py
rpmlint/arparser.py
rpmlint/cli.py
rpmlint/color.py
rpmlint/config.py
rpmlint/configdefaults.toml
rpmlint/filter.py
rpmlint/helpers.py
rpmlint/lddparser.py
rpmlint/lint.py
rpmlint/objdumpparser.py
rpmlint/pkg.py
rpmlint/pkgfile.py
rpmlint/readelfparser.py
rpmlint/rpmdiff.py
rpmlint/spellcheck.py
rpmlint/stringsparser.py
rpmlint/version.py
rpmlint.egg-info/PKG-INFO
rpmlint.egg-info/SOURCES.txt
rpmlint.egg-info/dependency_links.txt
rpmlint.egg-info/entry_points.txt
rpmlint.egg-info/requires.txt
rpmlint.egg-info/top_level.txt
rpmlint/checks/AbstractCheck.py
rpmlint/checks/AlternativesCheck.py
rpmlint/checks/AppDataCheck.py
rpmlint/checks/BashismsCheck.py
rpmlint/checks/BinariesCheck.py
rpmlint/checks/BuildRootAndDateCheck.py
rpmlint/checks/ConfigFilesCheck.py
rpmlint/checks/DBusPolicyCheck.py
rpmlint/checks/DocCheck.py
rpmlint/checks/DuplicatesCheck.py
rpmlint/checks/ErlangCheck.py
rpmlint/checks/FHSCheck.py
rpmlint/checks/FilesCheck.py
rpmlint/checks/I18NCheck.py
rpmlint/checks/IconSizesCheck.py
rpmlint/checks/InitScriptCheck.py
rpmlint/checks/LSBCheck.py
rpmlint/checks/LibraryDependencyCheck.py
rpmlint/checks/LogrotateCheck.py
rpmlint/checks/MenuCheck.py
rpmlint/checks/MenuXDGCheck.py
rpmlint/checks/MixedOwnershipCheck.py
rpmlint/checks/PAMModulesCheck.py
rpmlint/checks/PkgConfigCheck.py
rpmlint/checks/PostCheck.py
rpmlint/checks/PythonCheck.py
rpmlint/checks/SharedLibraryPolicyCheck.py
rpmlint/checks/SignatureCheck.py
rpmlint/checks/SourceCheck.py
rpmlint/checks/SpecCheck.py
rpmlint/checks/SysVInitOnSystemdCheck.py
rpmlint/checks/TagsCheck.py
rpmlint/checks/TmpFilesCheck.py
rpmlint/checks/XinetdDepCheck.py
rpmlint/checks/ZipCheck.py
