Metadata-Version: 2.1
Name: rpmlint
Version: 2.8.0
Summary: Check for common errors in RPM packages
Author-email: Frédéric Lepied <flepied@mandriva.com>
Maintainer-email: RPMLint maintainers <rpm-ecosystem@lists.rpm.org>
License: License :: OSI Approved :: GNU General Public License v2 or later (GPLv2+)
Project-URL: homepage, https://github.com/rpm-software-management/rpmlint
Project-URL: download-url, https://github.com/rpm-software-management/rpmlint
Keywords: RPM,.spec,validator
Platform: Linux
Classifier: Development Status :: 5 - Production/Stable
Classifier: Intended Audience :: Developers
Classifier: License :: OSI Approved :: GNU General Public License v2 or later (GPLv2+)
Classifier: Operating System :: Unix
Classifier: Operating System :: POSIX
Classifier: Operating System :: POSIX :: Linux
Classifier: Programming Language :: Python
Classifier: Programming Language :: Python :: 3.8
Classifier: Programming Language :: Python :: 3.9
Classifier: Programming Language :: Python :: 3.10
Classifier: Topic :: Utilities
Classifier: Topic :: Software Development :: Quality Assurance
Classifier: Topic :: System :: Archiving :: Packaging
License-File: COPYING
Requires-Dist: pybeam
Requires-Dist: pyxdg
Requires-Dist: rpm
Requires-Dist: tomli; python_version < "3.11"
Requires-Dist: tomli-w
Requires-Dist: zstandard
Requires-Dist: importlib-metadata; python_version < "3.8"
Requires-Dist: pyenchant
Requires-Dist: python-magic
Requires-Dist: packaging
Provides-Extra: test
Requires-Dist: pytest; extra == "test"
Requires-Dist: pytest-cov; extra == "test"
Requires-Dist: pytest-xdist; extra == "test"
